<annotation>
	<filename>319.jpg</filename>
	<size>
		<width>1280</width>
		<height>720</height>
		<depth>3</depth>
	</size>
	<object>
		<name>weed</name>
		<bndbox>
			<xmin>631</xmin>
			<ymin>194</ymin>
			<xmax>699</xmax>
			<ymax>265</ymax>
		</bndbox>
	</object>
	<object>
		<name>weed</name>
		<bndbox>
			<xmin>947</xmin>
			<ymin>267</ymin>
			<xmax>984</xmax>
			<ymax>307</ymax>
		</bndbox>
	</object>
	<object>
		<name>weed</name>
		<bndbox>
			<xmin>1112</xmin>
			<ymin>289</ymin>
			<xmax>1170</xmax>
			<ymax>356</ymax>
		</bndbox>
	</object>
	<object>
		<name>weed</name>
		<bndbox>
			<xmin>682</xmin>
			<ymin>436</ymin>
			<xmax>706</xmax>
			<ymax>466</ymax>
		</bndbox>
	</object>
	<object>
		<name>weed</name>
		<bndbox>
			<xmin>614</xmin>
			<ymin>524</ymin>
			<xmax>643</xmax>
			<ymax>562</ymax>
		</bndbox>
	</object>
	<object>
		<name>weed</name>
		<bndbox>
			<xmin>634</xmin>
			<ymin>282</ymin>
			<xmax>660</xmax>
			<ymax>351</ymax>
		</bndbox>
	</object>
	<object>
		<name>weed</name>
		<bndbox>
			<xmin>645</xmin>
			<ymin>373</ymin>
			<xmax>670</xmax>
			<ymax>397</ymax>
		</bndbox>
	</object>
</annotation>